flask_rq2/__init__.py
flask_rq2/app.py
flask_rq2/cli.py
flask_rq2/functions.py
flask_rq2/job.py
flask_rq2/scheduler.py
Flask_RQ2-18.2.2.dist-info/AUTHORS
Flask_RQ2-18.2.2.dist-info/LICENSE
Flask_RQ2-18.2.2.dist-info/METADATA
Flask_RQ2-18.2.2.dist-info/WHEEL
Flask_RQ2-18.2.2.dist-info/top_level.txt
Flask_RQ2-18.2.2.dist-info/RECORD
