Metadata-Version: 2.1
Name: Flask-RQ2
Version: 18.2.2
Summary: A Flask extension for RQ.
Home-page: https://flask-rq2.readthedocs.io/
Author: Jannis Leidel
Author-email: jannis@leidel.info
License: MIT
Platform: any
Classifier: Development Status :: 5 - Production/Stable
Classifier: Programming Language :: Python :: 2
Classifier: Programming Language :: Python :: 2.7
Classifier: Programming Language :: Python :: 3
Classifier: Programming Language :: Python :: 3.5
Classifier: Programming Language :: Python :: 3.6
Classifier: Programming Language :: Python :: 3.7
Classifier: Environment :: Web Environment
Classifier: Intended Audience :: Developers
Classifier: Intended Audience :: End Users/Desktop
Classifier: Intended Audience :: Information Technology
Classifier: Intended Audience :: Science/Research
Classifier: Intended Audience :: System Administrators 
Classifier: License :: OSI Approved :: MIT License
Classifier: Operating System :: MacOS
Classifier: Operating System :: POSIX
Classifier: Operating System :: Unix 
Classifier: Programming Language :: Python
Classifier: Topic :: Internet
Classifier: Topic :: Scientific/Engineering
Classifier: Topic :: Software Development :: Libraries :: Python Modules
Classifier: Topic :: System :: Distributed Computing
Classifier: Topic :: System :: Monitoring
Classifier: Topic :: System :: Systems Administration
Requires-Dist: Flask (>=0.10)
Requires-Dist: rq (<0.13.0,>=0.12.0)
Requires-Dist: redis (<3.0.0)
Requires-Dist: rq-scheduler (<0.9.0,>=0.8.3)
Provides-Extra: all
Requires-Dist: Sphinx (>=1.4) ; extra == 'all'
Requires-Dist: pytest ; extra == 'all'
Requires-Dist: redis (<3.0.0) ; extra == 'all'
Requires-Dist: rq-scheduler (<0.9.0,>=0.8.3) ; extra == 'all'
Requires-Dist: flask-cli (>=0.4.0) ; extra == 'all'
Requires-Dist: pytest (>=2.8.0) ; extra == 'all'
Requires-Dist: pytest-cache (>=1.0) ; extra == 'all'
Requires-Dist: pytest-flake8 (>=0.5) ; extra == 'all'
Requires-Dist: pytest-wholenodeid ; extra == 'all'
Requires-Dist: pytest-coverage ; extra == 'all'
Requires-Dist: pytest-pythonpath ; extra == 'all'
Requires-Dist: Flask-CLI (>=0.4.0) ; extra == 'all'
Provides-Extra: cli
Requires-Dist: Flask-CLI (>=0.4.0) ; extra == 'cli'
Provides-Extra: docs
Requires-Dist: Sphinx (>=1.4) ; extra == 'docs'
Provides-Extra: tests
Requires-Dist: pytest ; extra == 'tests'
Requires-Dist: redis (<3.0.0) ; extra == 'tests'
Requires-Dist: rq-scheduler (<0.9.0,>=0.8.3) ; extra == 'tests'
Requires-Dist: flask-cli (>=0.4.0) ; extra == 'tests'
Requires-Dist: pytest (>=2.8.0) ; extra == 'tests'
Requires-Dist: pytest-cache (>=1.0) ; extra == 'tests'
Requires-Dist: pytest-flake8 (>=0.5) ; extra == 'tests'
Requires-Dist: pytest-wholenodeid ; extra == 'tests'
Requires-Dist: pytest-coverage ; extra == 'tests'
Requires-Dist: pytest-pythonpath ; extra == 'tests'
